{
  "asOf": 1761853214,
  "chainId": 8453,
  "distributor": "0x781a80fa817b5a146c440f03ef8643f4aca6588a",
  "lastUpdated": "2025-10-30T19:40:14.954872",
  "liqDistributor": "0xb81efc6be6622bf4086566210a6ad134cd0cdda4",
  "liqSnapshot": {
    "balances": [
      {
        "address": "0x00fbac94fec8d4089d3fe979f39454f48c71a65d",
        "balance": "612852894728070498",
        "balanceUsd": 0.068172887394,
        "decimals": 18,
        "priceUsd": 0.11123858266837522
      },
      {
        "address": "0x04c0599ae5a44757c0af6f9ec3b93da8976c150a",
        "balance": "493320",
        "balanceUsd": 1.979e-09,
        "decimals": 18,
        "priceUsd": 4012.0144778509552
      },
      {
        "address": "0x07d15798a67253d76cea61f0ea6f57aedc59dffb",
        "balance": "0",
        "balanceUsd": 0.0,
        "decimals": 18,
        "priceUsd": 1.9627390232634032e-05
      },
      {
        "address": "0x084382d1cc4f4dfd1769b1cc1ac2a9b1f8365e90",
        "balance": "706158298320468",
        "balanceUsd": 5.80075e-07,
        "decimals": 18,
        "priceUsd": 0.000821451959701395
      },
      {
        "address": "0x0b3e328455c4059eeb9e3f84b5543f74e24e7e1b",
        "balance": "5386578022178607",
        "balanceUsd": 0.00664489984,
        "decimals": 18,
        "priceUsd": 1.2336031915847747
      },
      {
        "address": "0x0c03ce270b4826ec62e7dd007f0b716068639f7b",
        "balance": "159666942077629033",
        "balanceUsd": 0.099807434494,
        "decimals": 18,
        "priceUsd": 0.6250976764219117
      },
      {
        "address": "0x0ceac003b0d2479bebec9f4b2ebad0a803759bbf",
        "balance": "0",
        "balanceUsd": 0.0,
        "decimals": 18,
        "priceUsd": 1.228758208824885
      },
      {
        "address": "0x11dc28d01984079b7efe7763b533e6ed9e3722b9",
        "balance": "26808493245997",
        "balanceUsd": 4.429158e-06,
        "decimals": 18,
        "priceUsd": 0.16521473525148128
      },
      {
        "address": "0x1217bfe6c773eec6cc4a38b5dc45b92292b6e189",
        "balance": "0",
        "balanceUsd": 0.0,
        "decimals": 6,
        "priceUsd": 0.9993683284302959
      },
      {
        "address": "0x1bc0c42215582d5a085795f4badbac3ff36d1bcb",
        "balance": "2719679952455106",
        "balanceUsd": 0.282397632273,
        "decimals": 18,
        "priceUsd": 103.834876606562
      },
      {
        "address": "0x1db0c569ebb4a8b57ac01833b9792f526305e062",
        "balance": "618896",
        "balanceUsd": 0.0,
        "decimals": 18,
        "priceUsd": 0.002491431292279901
      },
      {
        "address": "0x2081ab0d9ec9e4303234ab26d86b20b3367946ee",
        "balance": "0",
        "balanceUsd": 0.0,
        "decimals": 18,
        "priceUsd": 0.920835088760825
      },
      {
        "address": "0x20fbd133897ef802e0235db77bb19a071e257d41",
        "balance": "12208866963516528975",
        "balanceUsd": 0.052363842432,
        "decimals": 18,
        "priceUsd": 0.004289000985008381
      },
      {
        "address": "0x226a2fa2556c48245e57cd1cba4c6c9e67077dd2",
        "balance": "63038810993573817",
        "balanceUsd": 0.004775563206,
        "decimals": 18,
        "priceUsd": 0.07575592132423149
      },
      {
        "address": "0x23471e7250bcd7ee21df3f39ed6151931d1e076b",
        "balance": "43017724328041634",
        "balanceUsd": 0.003802853247,
        "decimals": 18,
        "priceUsd": 0.0884020088542493
      },
      {
        "address": "0x236aa50979d5f3de3bd1eeb40e81137f22ab794b",
        "balance": "556995443361",
        "balanceUsd": 0.0,
        "decimals": 18,
        "priceUsd": 0.0
      },
      {
        "address": "0x24fcfc492c1393274b6bcd568ac9e225bec93584",
        "balance": "656375",
        "balanceUsd": 0.0,
        "decimals": 18,
        "priceUsd": 0.10903090942691321
      },
      {
        "address": "0x25dcf191058288edcbe1597a4c2d8dea0943acae",
        "balance": "0",
        "balanceUsd": 0.0,
        "decimals": 18,
        "priceUsd": 0.0
      },
      {
        "address": "0x2615a94df961278dcbc41fb0a54fec5f10a693ae",
        "balance": "4108366373806164",
        "balanceUsd": 0.009979071293,
        "decimals": 18,
        "priceUsd": 2.4289633360250087
      },
      {
        "address": "0x26f3901ac8a79c50fb0d8289c74f0d09adc42e29",
        "balance": "0",
        "balanceUsd": 0.0,
        "decimals": 18,
        "priceUsd": 0.011891239940725802
      },
      {
        "address": "0x2a0a59d6b975828e781ecac125dba40d7ee5ddc0",
        "balance": "0",
        "balanceUsd": 0.0,
        "decimals": 18,
        "priceUsd": 1.6979388793703518
      },
      {
        "address": "0x2d6613f383a89742179fdbdf3649b5dddec523c6",
        "balance": "1",
        "balanceUsd": 0.0,
        "decimals": 18,
        "priceUsd": 0.0
      },
      {
        "address": "0x2dad3a13ef0c6366220f989157009e501e7938f8",
        "balance": "0",
        "balanceUsd": 0.0,
        "decimals": 18,
        "priceUsd": 0.01603603648420186
      },
      {
        "address": "0x30c7235866872213f68cb1f08c37cb9eccb93452",
        "balance": "117258103473546562",
        "balanceUsd": 0.008683044496,
        "decimals": 18,
        "priceUsd": 0.07405069874974325
      },
      {
        "address": "0x3319e7bd7e8792f313aef8f572cbb0470bfd38a2",
        "balance": "1",
        "balanceUsd": 0.0,
        "decimals": 18,
        "priceUsd": 0.0
      },
      {
        "address": "0x3489256febdb1dc930dc3743617ad387cd6d3568",
        "balance": "0",
        "balanceUsd": 0.0,
        "decimals": 18,
        "priceUsd": 0.10960517868511054
      },
      {
        "address": "0x39d5313c3750140e5042887413ba8aa6145a9bd2",
        "balance": "138452",
        "balanceUsd": 3e-12,
        "decimals": 18,
        "priceUsd": 24.2659745489527
      },
      {
        "address": "0x3e31966d4f81c72d2a55310a6365a56a4393e98d",
        "balance": "5354534",
        "balanceUsd": 0.722755707771,
        "decimals": 6,
        "priceUsd": 0.13498013230860892
      },
      {
        "address": "0x4200000000000000000000000000000000000006",
        "balance": "808238614876399",
        "balanceUsd": 2.996762640961,
        "decimals": 18,
        "priceUsd": 3707.769693012591
      },
      {
        "address": "0x430d3834c385b5064050bf73c725ecc614111140",
        "balance": "1",
        "balanceUsd": 0.0,
        "decimals": 18,
        "priceUsd": 0.0
      },
      {
        "address": "0x449b3317a6d1efb1bc3ba0700c9eaa4ffff4ae65",
        "balance": "907174",
        "balanceUsd": 0.595298597505,
        "decimals": 6,
        "priceUsd": 0.6562121461874357
      },
      {
        "address": "0x4621b7a9c75199271f773ebd9a499dbd165c3191",
        "balance": "15598636673",
        "balanceUsd": 1.5542e-08,
        "decimals": 18,
        "priceUsd": 0.996364910215293
      },
      {
        "address": "0x4da9a0f397db1397902070f93a4d6ddbc0e0e6e8",
        "balance": "3606670562703076",
        "balanceUsd": 0.038385542752,
        "decimals": 18,
        "priceUsd": 10.642930116592794
      },
      {
        "address": "0x4e200fe2f3efb977d5fd9c430a41531fb04d97b8",
        "balance": "0",
        "balanceUsd": 0.0,
        "decimals": 18,
        "priceUsd": 0.20961516149621906
      },
      {
        "address": "0x4e74d4db6c0726ccded4656d0bce448876bb4c7a",
        "balance": "84154081921049600",
        "balanceUsd": 0.093322507067,
        "decimals": 18,
        "priceUsd": 1.1089480740205913
      },
      {
        "address": "0x4ed4e862860bed51a9570b96d89af5e1b0efefed",
        "balance": "16381062107034118228",
        "balanceUsd": 0.029383496733,
        "decimals": 18,
        "priceUsd": 0.0017937479597759244
      },
      {
        "address": "0x4f9fd6be4a90f2620860d680c0d4d5fb53d1a825",
        "balance": "152635289862587677",
        "balanceUsd": 0.010009443395,
        "decimals": 18,
        "priceUsd": 0.06557751751924819
      },
      {
        "address": "0x50da645f148798f68ef2d7db7c1cb22a6819bb2c",
        "balance": "3131617",
        "balanceUsd": 0.027186077824,
        "decimals": 8,
        "priceUsd": 0.8681163061712353
      },
      {
        "address": "0x548f93779fbc992010c07467cbaf329dd5f059b7",
        "balance": "10544107902416020",
        "balanceUsd": 0.075553507626,
        "decimals": 18,
        "priceUsd": 7.165471780583676
      },
      {
        "address": "0x56f8ad6112c2db9f9848243531b277ce1c3be30c",
        "balance": "6478360114227127431",
        "balanceUsd": 0.026734483115,
        "decimals": 18,
        "priceUsd": 0.00412673618684245
      },
      {
        "address": "0x58538e6a46e07434d7e7375bc268d3cb839c0133",
        "balance": "520357067000",
        "balanceUsd": 2.01567e-07,
        "decimals": 18,
        "priceUsd": 0.3873633287107036
      },
      {
        "address": "0x590830dfdf9a3f68afcdde2694773debdf267774",
        "balance": "0",
        "balanceUsd": 0.0,
        "decimals": 18,
        "priceUsd": 0.08958727384140588
      },
      {
        "address": "0x5ab3d4c385b400f3abb49e80de2faf6a88a7b691",
        "balance": "273514797252596722",
        "balanceUsd": 0.057232017973,
        "decimals": 18,
        "priceUsd": 0.20924651443902068
      },
      {
        "address": "0x616b416f777e3dc904a44aa259a475bf26d06ef9",
        "balance": "378988544171610",
        "balanceUsd": 4.32327e-07,
        "decimals": 18,
        "priceUsd": 0.0011407389118767365
      },
      {
        "address": "0x6444c6c2d527d85ea97032da9a7504d6d1448ecf",
        "balance": "0",
        "balanceUsd": 0.0,
        "decimals": 18,
        "priceUsd": 0.6300353845779184
      },
      {
        "address": "0x674b82f208b453c22310b47ae134984b14b4a407",
        "balance": "250000000000000000000000000",
        "balanceUsd": 0.0,
        "decimals": 18,
        "priceUsd": 0.0
      },
      {
        "address": "0x688aee022aa544f150678b8e5720b6b96a9e9a2f",
        "balance": "112471830257388112",
        "balanceUsd": 0.043725829678,
        "decimals": 18,
        "priceUsd": 0.3887713890495506
      },
      {
        "address": "0x696f9436b67233384889472cd7cd58a6fb5df4f1",
        "balance": "2128986874702058327",
        "balanceUsd": 1.216104895991,
        "decimals": 18,
        "priceUsd": 0.5712129607003567
      },
      {
        "address": "0x6985884c4392d348587b19cb9eaaf157f13271cd",
        "balance": "24471289976214570",
        "balanceUsd": 0.036918999066,
        "decimals": 18,
        "priceUsd": 1.508665832579991
      },
      {
        "address": "0x6b2504a03ca4d43d0d73776f6ad46dab2f2a4cfd",
        "balance": "0",
        "balanceUsd": 0.0,
        "decimals": 18,
        "priceUsd": 0.02815767253983324
      },
      {
        "address": "0x6c240dda6b5c336df09a4d011139beaaa1ea2aa2",
        "balance": "104506474547",
        "balanceUsd": 8.9101e-08,
        "decimals": 18,
        "priceUsd": 0.8525891893416955
      },
      {
        "address": "0x6e2c81b6c2c0e02360f00a0da694e489acb0b05e",
        "balance": "233227119455894089",
        "balanceUsd": 0.010735574222,
        "decimals": 18,
        "priceUsd": 0.04603055702342659
      },
      {
        "address": "0x7300b37dfdfab110d83290a29dfb31b1740219fe",
        "balance": "4664672605832857963",
        "balanceUsd": 0.239029105023,
        "decimals": 18,
        "priceUsd": 0.051242418326308485
      },
      {
        "address": "0x7431ada8a591c955a994a21710752ef9b882b8e3",
        "balance": "26564213846217121",
        "balanceUsd": 0.071799761816,
        "decimals": 18,
        "priceUsd": 2.702875463659745
      },
      {
        "address": "0x7750741868cc4a865d9c0f619e6e642fd61f642f",
        "balance": "37023480182777",
        "balanceUsd": 1.265653e-06,
        "decimals": 18,
        "priceUsd": 0.03418514840742646
      },
      {
        "address": "0x7750c092e284e2c7366f50c8306f43c7eb2e82a2",
        "balance": "0",
        "balanceUsd": 0.0,
        "decimals": 18,
        "priceUsd": 0.28286340397231835
      },
      {
        "address": "0x78b3c724a2f663d11373c4a1978689271895256f",
        "balance": "1293050239024",
        "balanceUsd": 9.924e-09,
        "decimals": 18,
        "priceUsd": 0.007674967794469145
      },
      {
        "address": "0x79bbf4508b1391af3a0f4b30bb5fc4aa9ab0e07c",
        "balance": "235444340000",
        "balanceUsd": 3.31516e-07,
        "decimals": 18,
        "priceUsd": 1.4080455466685993
      },
      {
        "address": "0x7aafd31a321d3627b30a8e2171264b56852187fe",
        "balance": "0",
        "balanceUsd": 0.0,
        "decimals": 18,
        "priceUsd": 0.2408132612520287
      },
      {
        "address": "0x7ba6f01772924a82d9626c126347a28299e98c98",
        "balance": "0",
        "balanceUsd": 0.0,
        "decimals": 18,
        "priceUsd": 3704.800778814887
      },
      {
        "address": "0x7e2a4abd22d513c34f347038d4b8c37cb3571f92",
        "balance": "1",
        "balanceUsd": 0.0,
        "decimals": 18,
        "priceUsd": 0.0
      },
      {
        "address": "0x800822d361335b4d5f352dac293ca4128b5b605f",
        "balance": "0",
        "balanceUsd": 0.0,
        "decimals": 18,
        "priceUsd": 0.011989394175500726
      },
      {
        "address": "0x806041b6473da60abbe1b256d9a2749a151be6c6",
        "balance": "0",
        "balanceUsd": 0.0,
        "decimals": 9,
        "priceUsd": 517.921665917649
      },
      {
        "address": "0x81034fb34009115f215f5d5f564aac9ffa46a1dc",
        "balance": "0",
        "balanceUsd": 0.0,
        "decimals": 18,
        "priceUsd": 0.0
      },
      {
        "address": "0x833589fcd6edb6e08f4c7c32d4f71b54bda02913",
        "balance": "6622259",
        "balanceUsd": 6.620346215642,
        "decimals": 6,
        "priceUsd": 0.9997111583285998
      },
      {
        "address": "0x8fe815417913a93ea99049fc0718ee1647a2a07c",
        "balance": "0",
        "balanceUsd": 0.0,
        "decimals": 18,
        "priceUsd": 0.0370494236075799
      },
      {
        "address": "0x93dc5cb35627a759848c7a7f0079ea7b49e435a5",
        "balance": "4398363949830554",
        "balanceUsd": 0.00238898774,
        "decimals": 18,
        "priceUsd": 0.543153719745213
      },
      {
        "address": "0x940181a94a35a4569e4529a3cdfb74e38fd98631",
        "balance": "1032082264216995904",
        "balanceUsd": 0.987918745518,
        "decimals": 18,
        "priceUsd": 0.9572093037253367
      },
      {
        "address": "0x9818b6c09f5ecc843060927e8587c427c7c93583",
        "balance": "1677316612613888355",
        "balanceUsd": 0.021942674721,
        "decimals": 18,
        "priceUsd": 0.01308201120513938
      },
      {
        "address": "0x98d0baa52b2d063e780de12f615f963fe8537553",
        "balance": "66502168358980793",
        "balanceUsd": 0.063861402016,
        "decimals": 18,
        "priceUsd": 0.9602905227308518
      },
      {
        "address": "0x9a26f5433671751c3276a065f57e5a02d2817973",
        "balance": "5224024260605",
        "balanceUsd": 9.663e-09,
        "decimals": 18,
        "priceUsd": 0.0018497017914298254
      },
      {
        "address": "0x9a33406165f562e16c3abd82fd1185482e01b49a",
        "balance": "3249779783064163938",
        "balanceUsd": 0.013043747591,
        "decimals": 18,
        "priceUsd": 0.004013732763953259
      },
      {
        "address": "0x9b8df6e244526ab5f6e6400d331db28c8fdddb55",
        "balance": "353437930288278",
        "balanceUsd": 0.0642095959,
        "decimals": 18,
        "priceUsd": 181.67149136442026
      },
      {
        "address": "0x9d0e8f5b25384c7310cb8c6ae32c8fbeb645d083",
        "balance": "434871761289102541",
        "balanceUsd": 0.015425306645,
        "decimals": 18,
        "priceUsd": 0.035470931934273815
      },
      {
        "address": "0x9d56c29e820dd13b0580b185d0e0dc301d27581d",
        "balance": "0",
        "balanceUsd": 0.0,
        "decimals": 18,
        "priceUsd": 7.926801890290005
      },
      {
        "address": "0x9d5c1c400dc828a3409f9c209b83ff51a65d2a0e",
        "balance": "7586218114844",
        "balanceUsd": 4.8558e-08,
        "decimals": 18,
        "priceUsd": 0.006400768133553298
      },
      {
        "address": "0xa4a2e2ca3fbfe21aed83471d28b6f65a233c6e00",
        "balance": "881655692932323413",
        "balanceUsd": 0.275065876325,
        "decimals": 18,
        "priceUsd": 0.3119878638901447
      },
      {
        "address": "0xa749de6c28262b7ffbc5de27dc845dd7ecd2b358",
        "balance": "1040104209102138812",
        "balanceUsd": 0.064917569353,
        "decimals": 18,
        "priceUsd": 0.06241448576442386
      },
      {
        "address": "0xa88594d404727625a9437c3f886c7643872296ae",
        "balance": "1050628823734662496",
        "balanceUsd": 0.016256858127,
        "decimals": 18,
        "priceUsd": 0.015473455286257246
      },
      {
        "address": "0xaaa843fb2916c0b57454270418e121c626402aaa",
        "balance": "5115455757475",
        "balanceUsd": 4.85718e-07,
        "decimals": 18,
        "priceUsd": 0.09495115081448142
      },
      {
        "address": "0xacfe6019ed1a7dc6f7b508c02d1b04ec88cc21bf",
        "balance": "0",
        "balanceUsd": 0.0,
        "decimals": 18,
        "priceUsd": 1.4513335234698523
      },
      {
        "address": "0xaea742f80922f7c94b8fd91686c9dfbdfe90d9e6",
        "balance": "8832112237132840803",
        "balanceUsd": 0.111199009163,
        "decimals": 18,
        "priceUsd": 0.012590307525286342
      },
      {
        "address": "0xafb89a09d82fbde58f18ac6437b3fc81724e4df6",
        "balance": "0",
        "balanceUsd": 0.0,
        "decimals": 18,
        "priceUsd": 0.001166730528194748
      },
      {
        "address": "0xb0505e5a99abd03d94a1169e638b78edfed26ea4",
        "balance": "42766221487025337",
        "balanceUsd": 0.095633540478,
        "decimals": 18,
        "priceUsd": 2.2361933589885097
      },
      {
        "address": "0xb0c26970e9dad9b5162fcaab1a5d13e604a6d9ac",
        "balance": "0",
        "balanceUsd": 0.0,
        "decimals": 18,
        "priceUsd": 0.0
      },
      {
        "address": "0xb0ffa8000886e57f86dd5264b9582b2ad87b2b91",
        "balance": "0",
        "balanceUsd": 0.0,
        "decimals": 18,
        "priceUsd": 0.060800934570248925
      },
      {
        "address": "0xb1a03eda10342529bbf8eb700a06c60441fef25d",
        "balance": "2465002235168322401",
        "balanceUsd": 0.04002616275,
        "decimals": 18,
        "priceUsd": 0.016237779495337234
      },
      {
        "address": "0xb33ff54b9f7242ef1593d2c9bcd8f9df46c77935",
        "balance": "10556668222793269656",
        "balanceUsd": 0.06738812332,
        "decimals": 18,
        "priceUsd": 0.00638346511395226
      },
      {
        "address": "0xb435cb9cee20efce58c452f646552c3ad744ed64",
        "balance": "1",
        "balanceUsd": 0.0,
        "decimals": 18,
        "priceUsd": 0.0
      },
      {
        "address": "0xb676f87a6e701f0de8de5ab91b56b66109766db1",
        "balance": "0",
        "balanceUsd": 0.0,
        "decimals": 18,
        "priceUsd": 0.07630321278554111
      },
      {
        "address": "0xb96a7fa2dc5627eb76f91962e1e45e75e572c850",
        "balance": "1",
        "balanceUsd": 0.0,
        "decimals": 18,
        "priceUsd": 0.0
      },
      {
        "address": "0xb9e1fd5a02d3a33b25a14d661414e6ed6954a721",
        "balance": "3134391092560155",
        "balanceUsd": 0.00233651917,
        "decimals": 18,
        "priceUsd": 0.7454459576607901
      },
      {
        "address": "0xbb22ff867f8ca3d5f2251b4084f6ec86d4666e14",
        "balance": "1260784710303",
        "balanceUsd": 1.477627e-06,
        "decimals": 18,
        "priceUsd": 1.171989618527419
      },
      {
        "address": "0xbcd73d9c3de8884c9aaaf9b2e4f0a48a64f12a1b",
        "balance": "1",
        "balanceUsd": 0.0,
        "decimals": 18,
        "priceUsd": 0.0
      },
      {
        "address": "0xbf927b841994731c573bdf09ceb0c6b0aa887cdd",
        "balance": "244162162204212046",
        "balanceUsd": 0.051351342208,
        "decimals": 18,
        "priceUsd": 0.21031654431617447
      },
      {
        "address": "0xc0041ef357b183448b235a8ea73ce4e4ec8c265f",
        "balance": "1283530219317699146",
        "balanceUsd": 0.099248572637,
        "decimals": 18,
        "priceUsd": 0.07732468713532828
      },
      {
        "address": "0xc08cd26474722ce93f4d0c34d16201461c10aa8c",
        "balance": "71842127745971437",
        "balanceUsd": 0.010291782149,
        "decimals": 18,
        "priceUsd": 0.14325553087284829
      },
      {
        "address": "0xc1cba3fcea344f92d9239c08c0568f6f2f0ee452",
        "balance": "0",
        "balanceUsd": 0.0,
        "decimals": 18,
        "priceUsd": 4539.994572541674
      },
      {
        "address": "0xc48823ec67720a04a9dfd8c7d109b2c3d6622094",
        "balance": "0",
        "balanceUsd": 0.0,
        "decimals": 18,
        "priceUsd": 0.0082391586862853
      },
      {
        "address": "0xc729777d0470f30612b1564fd96e8dd26f5814e3",
        "balance": "0",
        "balanceUsd": 0.0,
        "decimals": 18,
        "priceUsd": 0.16218964038304937
      },
      {
        "address": "0xca73ed1815e5915489570014e024b7ebe65de679",
        "balance": "0",
        "balanceUsd": 0.0,
        "decimals": 18,
        "priceUsd": 0.0033857310442809993
      },
      {
        "address": "0xcbb7c0000ab88b473b1f5afd9ef808440eed33bf",
        "balance": "31750",
        "balanceUsd": 0.0,
        "decimals": 8,
        "priceUsd": 0.0
      },
      {
        "address": "0xcd2f22236dd9dfe2356d7c543161d4d260fd9bcb",
        "balance": "0",
        "balanceUsd": 0.0,
        "decimals": 18,
        "priceUsd": 0.2827269125604089
      },
      {
        "address": "0xd01c8f05a9b7d5c2672a590b563ced2cb50d24a6",
        "balance": "1",
        "balanceUsd": 0.0,
        "decimals": 18,
        "priceUsd": 0.0
      },
      {
        "address": "0xd24ea96b9bf1af69d34e7fc8c6d740bae5f32b9b",
        "balance": "1",
        "balanceUsd": 0.0,
        "decimals": 18,
        "priceUsd": 0.0
      },
      {
        "address": "0xd262a4c7108c8139b2b189758e8d17c3dfc91a38",
        "balance": "0",
        "balanceUsd": 0.0,
        "decimals": 18,
        "priceUsd": 0.05072734278569005
      },
      {
        "address": "0xd403d1624daef243fbcbd4a80d8a6f36affe32b2",
        "balance": "0",
        "balanceUsd": 0.0,
        "decimals": 18,
        "priceUsd": 16.932815275483616
      },
      {
        "address": "0xd4554bea546efa83c1e6b389ecac40ea999b3e78",
        "balance": "1094239094784420586",
        "balanceUsd": 0.108382204538,
        "decimals": 18,
        "priceUsd": 0.09904800975852734
      },
      {
        "address": "0xd769d56f479e9e72a77bb1523e866a33098feec5",
        "balance": "8941825451219095870",
        "balanceUsd": 0.025974820413,
        "decimals": 18,
        "priceUsd": 0.0029048677537211833
      },
      {
        "address": "0xda932bcc910ec2dbdcbc49e01f8a5b36be9deefb",
        "balance": "1",
        "balanceUsd": 0.0,
        "decimals": 18,
        "priceUsd": 0.0
      },
      {
        "address": "0xdbfefd2e8460a6ee4955a68582f85708baea60a3",
        "balance": "13555576914956",
        "balanceUsd": 0.050518557716,
        "decimals": 18,
        "priceUsd": 3726.772975648495
      },
      {
        "address": "0xdcefd8c8fcc492630b943abcab3429f12ea9fea2",
        "balance": "241459750",
        "balanceUsd": 0.031702080901,
        "decimals": 9,
        "priceUsd": 0.1312934387674124
      },
      {
        "address": "0xe1bfa25468af64e366ddafc9d91bcc6c97439a14",
        "balance": "3305153454684571736",
        "balanceUsd": 0.02991237846,
        "decimals": 18,
        "priceUsd": 0.009050223800508609
      },
      {
        "address": "0xe22c243c7559c667a1eb94b593369d192c5fbac0",
        "balance": "0",
        "balanceUsd": 0.0,
        "decimals": 18,
        "priceUsd": 701.1388238102584
      },
      {
        "address": "0xe5020a6d073a794b6e7f05678707de47986fb0b6",
        "balance": "0",
        "balanceUsd": 0.0,
        "decimals": 18,
        "priceUsd": 0.9994565423870788
      },
      {
        "address": "0xe642657e4f43e6dcf0bd73ef24008394574dee28",
        "balance": "0",
        "balanceUsd": 0.0,
        "decimals": 18,
        "priceUsd": 0.000383832990948164
      },
      {
        "address": "0xeab49138ba2ea6dd776220fe26b7b8e446638956",
        "balance": "0",
        "balanceUsd": 0.0,
        "decimals": 18,
        "priceUsd": 0.07155473954334658
      },
      {
        "address": "0xed6e000def95780fb89734c07ee2ce9f6dcaf110",
        "balance": "47966710870519094",
        "balanceUsd": 0.014630116385,
        "decimals": 18,
        "priceUsd": 0.305005619927976
      },
      {
        "address": "0xed7b04a3fdcc4b0718f76ab796d58f39212815cc",
        "balance": "1000000000000000000",
        "balanceUsd": 0.0,
        "decimals": 18,
        "priceUsd": 0.0
      },
      {
        "address": "0xeec468333ccc16d4bf1cef497a56cf8c0aae4ca3",
        "balance": "5839734145998069",
        "balanceUsd": 5.684482e-06,
        "decimals": 18,
        "priceUsd": 0.0009734144515180839
      },
      {
        "address": "0xef4461891dfb3ac8572ccf7c794664a8dd927945",
        "balance": "1401309478501408942",
        "balanceUsd": 0.196935054666,
        "decimals": 18,
        "priceUsd": 0.14053644657908199
      },
      {
        "address": "0xf1a7000000950c7ad8aff13118bb7ab561a448ee",
        "balance": "0",
        "balanceUsd": 0.0,
        "decimals": 18,
        "priceUsd": 0.02285780102391797
      },
      {
        "address": "0xf3df0a31ec5ea438150987805e841f960b9471b6",
        "balance": "3324268806856",
        "balanceUsd": 1.18189e-07,
        "decimals": 18,
        "priceUsd": 0.035553506858090445
      },
      {
        "address": "0xf43eb8de897fbc7f2502483b2bef7bb9ea179229",
        "balance": "7749871365670415",
        "balanceUsd": 0.08673521775,
        "decimals": 18,
        "priceUsd": 11.191826761718815
      },
      {
        "address": "0xf4d97f2da56e8c3098f3a8d538db630a2606a024",
        "balance": "0",
        "balanceUsd": 0.0,
        "decimals": 18,
        "priceUsd": 131.10586231808193
      },
      {
        "address": "0xf544251d25f3d243a36b07e7e7962a678f952691",
        "balance": "351990033416637011",
        "balanceUsd": 0.027552553777,
        "decimals": 18,
        "priceUsd": 0.07827651683740117
      },
      {
        "address": "0xf7c1cefcf7e1dd8161e00099facd3e1db9e528ee",
        "balance": "3747962112914935",
        "balanceUsd": 3.363225e-06,
        "decimals": 18,
        "priceUsd": 0.0008973477520197179
      },
      {
        "address": "0xfaf87e196a29969094be35dfb0ab9d0b8518db84",
        "balance": "100",
        "balanceUsd": 0.0,
        "decimals": 6,
        "priceUsd": 0.0
      },
      {
        "address": "0xfb584ace7f491e2930491a8d01a28db308aeb65f",
        "balance": "1",
        "balanceUsd": 0.0,
        "decimals": 18,
        "priceUsd": 0.0
      },
      {
        "address": "0xfc48314ad4ad5bd36a84e8307b86a68a01d95d9c",
        "balance": "0",
        "balanceUsd": 0.0,
        "decimals": 18,
        "priceUsd": 0.20660482594612717
      },
      {
        "address": "0xfd755cff1f0f65c1e163b33c66a0e082ce6f87ff",
        "balance": "1",
        "balanceUsd": 0.0,
        "decimals": 18,
        "priceUsd": 0.0
      },
      {
        "address": "0xfde4c96c8593536e31f229ea8f37b2ada2699bb2",
        "balance": "5511558",
        "balanceUsd": 5.509993911882,
        "decimals": 6,
        "priceUsd": 0.9997162166999343
      }
    ],
    "minUsd": 1.0
  },
  "liqState": {
    "last_tx_hash": "0xe53a50407596e96260ae7bf36939e67ac782df9d4f33b0714fdc15e3f7a2e31d",
    "last_update": 1761853214
  },
  "liqTokens": [
    {
      "address": "0x4200000000000000000000000000000000000006",
      "decimals": 18,
      "priceUsd": 3707.769693012591,
      "source": "llama"
    },
    {
      "address": "0x696f9436b67233384889472cd7cd58a6fb5df4f1",
      "decimals": 18,
      "priceUsd": 0.5712129607003567,
      "source": "llama"
    },
    {
      "address": "0x833589fcd6edb6e08f4c7c32d4f71b54bda02913",
      "decimals": 6,
      "priceUsd": 0.9997111583285998,
      "source": "llama"
    },
    {
      "address": "0xfde4c96c8593536e31f229ea8f37b2ada2699bb2",
      "decimals": 6,
      "priceUsd": 0.9997162166999343,
      "source": "llama"
    }
  ],
  "snapshot": {
    "balances": [
      {
        "address": "0x00fbac94fec8d4089d3fe979f39454f48c71a65d",
        "balance": "10514381011968139",
        "balanceUsd": 0.001169604841,
        "decimals": 18,
        "priceUsd": 0.11123858266837522
      },
      {
        "address": "0x04c0599ae5a44757c0af6f9ec3b93da8976c150a",
        "balance": "10754076",
        "balanceUsd": 4.3146e-08,
        "decimals": 18,
        "priceUsd": 4012.0144778509552
      },
      {
        "address": "0x07d15798a67253d76cea61f0ea6f57aedc59dffb",
        "balance": "1500000000000000000000",
        "balanceUsd": 0.029441085349,
        "decimals": 18,
        "priceUsd": 1.9627390232634032e-05
      },
      {
        "address": "0x084382d1cc4f4dfd1769b1cc1ac2a9b1f8365e90",
        "balance": "53200134990870587",
        "balanceUsd": 4.3701355e-05,
        "decimals": 18,
        "priceUsd": 0.000821451959701395
      },
      {
        "address": "0x0b3e328455c4059eeb9e3f84b5543f74e24e7e1b",
        "balance": "92414564956270",
        "balanceUsd": 0.000114002902,
        "decimals": 18,
        "priceUsd": 1.2336031915847747
      },
      {
        "address": "0x0c03ce270b4826ec62e7dd007f0b716068639f7b",
        "balance": "0",
        "balanceUsd": 0.0,
        "decimals": 18,
        "priceUsd": 0.6250976764219117
      },
      {
        "address": "0x0ceac003b0d2479bebec9f4b2ebad0a803759bbf",
        "balance": "877258566213",
        "balanceUsd": 1.077939e-06,
        "decimals": 18,
        "priceUsd": 1.228758208824885
      },
      {
        "address": "0x11dc28d01984079b7efe7763b533e6ed9e3722b9",
        "balance": "2342851169606801",
        "balanceUsd": 0.000387073536,
        "decimals": 18,
        "priceUsd": 0.16521473525148128
      },
      {
        "address": "0x1217bfe6c773eec6cc4a38b5dc45b92292b6e189",
        "balance": "2",
        "balanceUsd": 1.998737e-06,
        "decimals": 6,
        "priceUsd": 0.9993683284302959
      },
      {
        "address": "0x1bc0c42215582d5a085795f4badbac3ff36d1bcb",
        "balance": "0",
        "balanceUsd": 0.0,
        "decimals": 18,
        "priceUsd": 103.834876606562
      },
      {
        "address": "0x1db0c569ebb4a8b57ac01833b9792f526305e062",
        "balance": "0",
        "balanceUsd": 0.0,
        "decimals": 18,
        "priceUsd": 0.002491431292279901
      },
      {
        "address": "0x2081ab0d9ec9e4303234ab26d86b20b3367946ee",
        "balance": "0",
        "balanceUsd": 0.0,
        "decimals": 18,
        "priceUsd": 0.920835088760825
      },
      {
        "address": "0x20fbd133897ef802e0235db77bb19a071e257d41",
        "balance": "0",
        "balanceUsd": 0.0,
        "decimals": 18,
        "priceUsd": 0.004289000985008381
      },
      {
        "address": "0x226a2fa2556c48245e57cd1cba4c6c9e67077dd2",
        "balance": "1081522308249254",
        "balanceUsd": 8.1931719e-05,
        "decimals": 18,
        "priceUsd": 0.07575592132423149
      },
      {
        "address": "0x23471e7250bcd7ee21df3f39ed6151931d1e076b",
        "balance": "738031504296680",
        "balanceUsd": 6.5243468e-05,
        "decimals": 18,
        "priceUsd": 0.0884020088542493
      },
      {
        "address": "0x236aa50979d5f3de3bd1eeb40e81137f22ab794b",
        "balance": "0",
        "balanceUsd": 0.0,
        "decimals": 18,
        "priceUsd": 0.0
      },
      {
        "address": "0x24fcfc492c1393274b6bcd568ac9e225bec93584",
        "balance": "3223092044871",
        "balanceUsd": 3.51417e-07,
        "decimals": 18,
        "priceUsd": 0.10903090942691321
      },
      {
        "address": "0x25dcf191058288edcbe1597a4c2d8dea0943acae",
        "balance": "0",
        "balanceUsd": 0.0,
        "decimals": 18,
        "priceUsd": 0.0
      },
      {
        "address": "0x2615a94df961278dcbc41fb0a54fec5f10a693ae",
        "balance": "70484988720402",
        "balanceUsd": 0.000171205453,
        "decimals": 18,
        "priceUsd": 2.4289633360250087
      },
      {
        "address": "0x26f3901ac8a79c50fb0d8289c74f0d09adc42e29",
        "balance": "0",
        "balanceUsd": 0.0,
        "decimals": 18,
        "priceUsd": 0.011891239940725802
      },
      {
        "address": "0x2a0a59d6b975828e781ecac125dba40d7ee5ddc0",
        "balance": "0",
        "balanceUsd": 0.0,
        "decimals": 18,
        "priceUsd": 1.6979388793703518
      },
      {
        "address": "0x2d6613f383a89742179fdbdf3649b5dddec523c6",
        "balance": "1",
        "balanceUsd": 0.0,
        "decimals": 18,
        "priceUsd": 0.0
      },
      {
        "address": "0x2dad3a13ef0c6366220f989157009e501e7938f8",
        "balance": "112418123756198",
        "balanceUsd": 1.802741e-06,
        "decimals": 18,
        "priceUsd": 0.01603603648420186
      },
      {
        "address": "0x30c7235866872213f68cb1f08c37cb9eccb93452",
        "balance": "2036494395583459",
        "balanceUsd": 0.000150803833,
        "decimals": 18,
        "priceUsd": 0.07405069874974325
      },
      {
        "address": "0x3319e7bd7e8792f313aef8f572cbb0470bfd38a2",
        "balance": "1",
        "balanceUsd": 0.0,
        "decimals": 18,
        "priceUsd": 0.0
      },
      {
        "address": "0x3489256febdb1dc930dc3743617ad387cd6d3568",
        "balance": "2885104520534",
        "balanceUsd": 3.16222e-07,
        "decimals": 18,
        "priceUsd": 0.10960517868511054
      },
      {
        "address": "0x39d5313c3750140e5042887413ba8aa6145a9bd2",
        "balance": "34087044424",
        "balanceUsd": 8.27155e-07,
        "decimals": 18,
        "priceUsd": 24.2659745489527
      },
      {
        "address": "0x3e31966d4f81c72d2a55310a6365a56a4393e98d",
        "balance": "0",
        "balanceUsd": 0.0,
        "decimals": 6,
        "priceUsd": 0.13498013230860892
      },
      {
        "address": "0x4200000000000000000000000000000000000006",
        "balance": "5924308186413",
        "balanceUsd": 0.021965970346,
        "decimals": 18,
        "priceUsd": 3707.769693012591
      },
      {
        "address": "0x430d3834c385b5064050bf73c725ecc614111140",
        "balance": "1",
        "balanceUsd": 0.0,
        "decimals": 18,
        "priceUsd": 0.0
      },
      {
        "address": "0x449b3317a6d1efb1bc3ba0700c9eaa4ffff4ae65",
        "balance": "1344",
        "balanceUsd": 0.000881949124,
        "decimals": 6,
        "priceUsd": 0.6562121461874357
      },
      {
        "address": "0x4621b7a9c75199271f773ebd9a499dbd165c3191",
        "balance": "1174839116655",
        "balanceUsd": 1.170568e-06,
        "decimals": 18,
        "priceUsd": 0.996364910215293
      },
      {
        "address": "0x4da9a0f397db1397902070f93a4d6ddbc0e0e6e8",
        "balance": "0",
        "balanceUsd": 0.0,
        "decimals": 18,
        "priceUsd": 10.642930116592794
      },
      {
        "address": "0x4e200fe2f3efb977d5fd9c430a41531fb04d97b8",
        "balance": "0",
        "balanceUsd": 0.0,
        "decimals": 18,
        "priceUsd": 0.20961516149621906
      },
      {
        "address": "0x4e74d4db6c0726ccded4656d0bce448876bb4c7a",
        "balance": "1456935681208061",
        "balanceUsd": 0.001615666018,
        "decimals": 18,
        "priceUsd": 1.1089480740205913
      },
      {
        "address": "0x4ed4e862860bed51a9570b96d89af5e1b0efefed",
        "balance": "0",
        "balanceUsd": 0.0,
        "decimals": 18,
        "priceUsd": 0.0017937479597759244
      },
      {
        "address": "0x4f9fd6be4a90f2620860d680c0d4d5fb53d1a825",
        "balance": "2618679959399754",
        "balanceUsd": 0.000171726531,
        "decimals": 18,
        "priceUsd": 0.06557751751924819
      },
      {
        "address": "0x50da645f148798f68ef2d7db7c1cb22a6819bb2c",
        "balance": "1472",
        "balanceUsd": 1.2778672e-05,
        "decimals": 8,
        "priceUsd": 0.8681163061712353
      },
      {
        "address": "0x548f93779fbc992010c07467cbaf329dd5f059b7",
        "balance": "180899476592048",
        "balanceUsd": 0.001296230095,
        "decimals": 18,
        "priceUsd": 7.165471780583676
      },
      {
        "address": "0x56f8ad6112c2db9f9848243531b277ce1c3be30c",
        "balance": "125666983937577533",
        "balanceUsd": 0.00051859449,
        "decimals": 18,
        "priceUsd": 0.00412673618684245
      },
      {
        "address": "0x58538e6a46e07434d7e7375bc268d3cb839c0133",
        "balance": "40598045507987",
        "balanceUsd": 1.5726194e-05,
        "decimals": 18,
        "priceUsd": 0.3873633287107036
      },
      {
        "address": "0x590830dfdf9a3f68afcdde2694773debdf267774",
        "balance": "11082604168279",
        "balanceUsd": 9.9286e-07,
        "decimals": 18,
        "priceUsd": 0.08958727384140588
      },
      {
        "address": "0x5ab3d4c385b400f3abb49e80de2faf6a88a7b691",
        "balance": "1400636754029027",
        "balanceUsd": 0.000293078359,
        "decimals": 18,
        "priceUsd": 0.20924651443902068
      },
      {
        "address": "0x616b416f777e3dc904a44aa259a475bf26d06ef9",
        "balance": "28552014115423960",
        "balanceUsd": 3.2570394e-05,
        "decimals": 18,
        "priceUsd": 0.0011407389118767365
      },
      {
        "address": "0x6444c6c2d527d85ea97032da9a7504d6d1448ecf",
        "balance": "1810185781533",
        "balanceUsd": 1.140481e-06,
        "decimals": 18,
        "priceUsd": 0.6300353845779184
      },
      {
        "address": "0x674b82f208b453c22310b47ae134984b14b4a407",
        "balance": "250000000000000000000000000",
        "balanceUsd": 0.0,
        "decimals": 18,
        "priceUsd": 0.0
      },
      {
        "address": "0x688aee022aa544f150678b8e5720b6b96a9e9a2f",
        "balance": "1929617509531139",
        "balanceUsd": 0.00075018008,
        "decimals": 18,
        "priceUsd": 0.3887713890495506
      },
      {
        "address": "0x696f9436b67233384889472cd7cd58a6fb5df4f1",
        "balance": "36525860223142465",
        "balanceUsd": 0.02086404476,
        "decimals": 18,
        "priceUsd": 0.5712129607003567
      },
      {
        "address": "0x6985884c4392d348587b19cb9eaaf157f13271cd",
        "balance": "419840501435190",
        "balanceUsd": 0.00063339902,
        "decimals": 18,
        "priceUsd": 1.508665832579991
      },
      {
        "address": "0x6b2504a03ca4d43d0d73776f6ad46dab2f2a4cfd",
        "balance": "0",
        "balanceUsd": 0.0,
        "decimals": 18,
        "priceUsd": 0.02815767253983324
      },
      {
        "address": "0x6c240dda6b5c336df09a4d011139beaaa1ea2aa2",
        "balance": "7976302219563",
        "balanceUsd": 6.800509e-06,
        "decimals": 18,
        "priceUsd": 0.8525891893416955
      },
      {
        "address": "0x6e2c81b6c2c0e02360f00a0da694e489acb0b05e",
        "balance": "4001349781269143",
        "balanceUsd": 0.000184184359,
        "decimals": 18,
        "priceUsd": 0.04603055702342659
      },
      {
        "address": "0x7300b37dfdfab110d83290a29dfb31b1740219fe",
        "balance": "23119062817935799",
        "balanceUsd": 0.001184676688,
        "decimals": 18,
        "priceUsd": 0.051242418326308485
      },
      {
        "address": "0x7431ada8a591c955a994a21710752ef9b882b8e3",
        "balance": "455747648510801",
        "balanceUsd": 0.001231829137,
        "decimals": 18,
        "priceUsd": 2.702875463659745
      },
      {
        "address": "0x7750741868cc4a865d9c0f619e6e642fd61f642f",
        "balance": "2789252662855662",
        "balanceUsd": 9.5351016e-05,
        "decimals": 18,
        "priceUsd": 0.03418514840742646
      },
      {
        "address": "0x7750c092e284e2c7366f50c8306f43c7eb2e82a2",
        "balance": "12205435976206",
        "balanceUsd": 3.452471e-06,
        "decimals": 18,
        "priceUsd": 0.28286340397231835
      },
      {
        "address": "0x78b3c724a2f663d11373c4a1978689271895256f",
        "balance": "97415035287987",
        "balanceUsd": 7.47657e-07,
        "decimals": 18,
        "priceUsd": 0.007674967794469145
      },
      {
        "address": "0x79bbf4508b1391af3a0f4b30bb5fc4aa9ab0e07c",
        "balance": "19263590323410",
        "balanceUsd": 2.7124013e-05,
        "decimals": 18,
        "priceUsd": 1.4080455466685993
      },
      {
        "address": "0x7aafd31a321d3627b30a8e2171264b56852187fe",
        "balance": "0",
        "balanceUsd": 0.0,
        "decimals": 18,
        "priceUsd": 0.2408132612520287
      },
      {
        "address": "0x7ba6f01772924a82d9626c126347a28299e98c98",
        "balance": "47576560",
        "balanceUsd": 1.76262e-07,
        "decimals": 18,
        "priceUsd": 3704.800778814887
      },
      {
        "address": "0x7e2a4abd22d513c34f347038d4b8c37cb3571f92",
        "balance": "1",
        "balanceUsd": 0.0,
        "decimals": 18,
        "priceUsd": 0.0
      },
      {
        "address": "0x800822d361335b4d5f352dac293ca4128b5b605f",
        "balance": "0",
        "balanceUsd": 0.0,
        "decimals": 18,
        "priceUsd": 0.011989394175500726
      },
      {
        "address": "0x806041b6473da60abbe1b256d9a2749a151be6c6",
        "balance": "6469779",
        "balanceUsd": 3.350838717799,
        "decimals": 9,
        "priceUsd": 517.921665917649
      },
      {
        "address": "0x81034fb34009115f215f5d5f564aac9ffa46a1dc",
        "balance": "2769856460286890222799123",
        "balanceUsd": 0.0,
        "decimals": 18,
        "priceUsd": 0.0
      },
      {
        "address": "0x833589fcd6edb6e08f4c7c32d4f71b54bda02913",
        "balance": "46763",
        "balanceUsd": 0.046749492897,
        "decimals": 6,
        "priceUsd": 0.9997111583285998
      },
      {
        "address": "0x8fe815417913a93ea99049fc0718ee1647a2a07c",
        "balance": "46136457088811",
        "balanceUsd": 1.709329e-06,
        "decimals": 18,
        "priceUsd": 0.0370494236075799
      },
      {
        "address": "0x93dc5cb35627a759848c7a7f0079ea7b49e435a5",
        "balance": "76888429890327",
        "balanceUsd": 4.1762237e-05,
        "decimals": 18,
        "priceUsd": 0.543153719745213
      },
      {
        "address": "0x940181a94a35a4569e4529a3cdfb74e38fd98631",
        "balance": "15429849728551119",
        "balanceUsd": 0.014769595715,
        "decimals": 18,
        "priceUsd": 0.9572093037253367
      },
      {
        "address": "0x9818b6c09f5ecc843060927e8587c427c7c93583",
        "balance": "28776801243037377",
        "balanceUsd": 0.000376458436,
        "decimals": 18,
        "priceUsd": 0.01308201120513938
      },
      {
        "address": "0x98d0baa52b2d063e780de12f615f963fe8537553",
        "balance": "1141920203464857",
        "balanceUsd": 0.001096575149,
        "decimals": 18,
        "priceUsd": 0.9602905227308518
      },
      {
        "address": "0x9a26f5433671751c3276a065f57e5a02d2817973",
        "balance": "492395151703171",
        "balanceUsd": 9.10784e-07,
        "decimals": 18,
        "priceUsd": 0.0018497017914298254
      },
      {
        "address": "0x9a33406165f562e16c3abd82fd1185482e01b49a",
        "balance": "57366797675777344",
        "balanceUsd": 0.000230254995,
        "decimals": 18,
        "priceUsd": 0.004013732763953259
      },
      {
        "address": "0x9b8df6e244526ab5f6e6400d331db28c8fdddb55",
        "balance": "6076143340943",
        "balanceUsd": 0.001103862022,
        "decimals": 18,
        "priceUsd": 181.67149136442026
      },
      {
        "address": "0x9d0e8f5b25384c7310cb8c6ae32c8fbeb645d083",
        "balance": "7460856314566791",
        "balanceUsd": 0.000264643527,
        "decimals": 18,
        "priceUsd": 0.035470931934273815
      },
      {
        "address": "0x9d56c29e820dd13b0580b185d0e0dc301d27581d",
        "balance": "0",
        "balanceUsd": 0.0,
        "decimals": 18,
        "priceUsd": 7.926801890290005
      },
      {
        "address": "0x9d5c1c400dc828a3409f9c209b83ff51a65d2a0e",
        "balance": "571525672221055",
        "balanceUsd": 3.658203e-06,
        "decimals": 18,
        "priceUsd": 0.006400768133553298
      },
      {
        "address": "0xa4a2e2ca3fbfe21aed83471d28b6f65a233c6e00",
        "balance": "15132399362464015",
        "balanceUsd": 0.004721124953,
        "decimals": 18,
        "priceUsd": 0.3119878638901447
      },
      {
        "address": "0xa749de6c28262b7ffbc5de27dc845dd7ecd2b358",
        "balance": "3776387012949696",
        "balanceUsd": 0.000235701253,
        "decimals": 18,
        "priceUsd": 0.06241448576442386
      },
      {
        "address": "0xa88594d404727625a9437c3f886c7643872296ae",
        "balance": "18075197586626327",
        "balanceUsd": 0.000279685762,
        "decimals": 18,
        "priceUsd": 0.015473455286257246
      },
      {
        "address": "0xaaa843fb2916c0b57454270418e121c626402aaa",
        "balance": "405615114484289",
        "balanceUsd": 3.8513622e-05,
        "decimals": 18,
        "priceUsd": 0.09495115081448142
      },
      {
        "address": "0xacfe6019ed1a7dc6f7b508c02d1b04ec88cc21bf",
        "balance": "458721641823",
        "balanceUsd": 6.65758e-07,
        "decimals": 18,
        "priceUsd": 1.4513335234698523
      },
      {
        "address": "0xaea742f80922f7c94b8fd91686c9dfbdfe90d9e6",
        "balance": "104862752915169224",
        "balanceUsd": 0.001320254307,
        "decimals": 18,
        "priceUsd": 0.012590307525286342
      },
      {
        "address": "0xafb89a09d82fbde58f18ac6437b3fc81724e4df6",
        "balance": "1070326756326325",
        "balanceUsd": 1.248783e-06,
        "decimals": 18,
        "priceUsd": 0.001166730528194748
      },
      {
        "address": "0xb0505e5a99abd03d94a1169e638b78edfed26ea4",
        "balance": "0",
        "balanceUsd": 0.0,
        "decimals": 18,
        "priceUsd": 2.2361933589885097
      },
      {
        "address": "0xb0c26970e9dad9b5162fcaab1a5d13e604a6d9ac",
        "balance": "20000000000000000000",
        "balanceUsd": 0.0,
        "decimals": 18,
        "priceUsd": 0.0
      },
      {
        "address": "0xb0ffa8000886e57f86dd5264b9582b2ad87b2b91",
        "balance": "0",
        "balanceUsd": 0.0,
        "decimals": 18,
        "priceUsd": 0.060800934570248925
      },
      {
        "address": "0xb1a03eda10342529bbf8eb700a06c60441fef25d",
        "balance": "42290691484041019",
        "balanceUsd": 0.000686706923,
        "decimals": 18,
        "priceUsd": 0.016237779495337234
      },
      {
        "address": "0xb33ff54b9f7242ef1593d2c9bcd8f9df46c77935",
        "balance": "54649672218307086",
        "balanceUsd": 0.000348854276,
        "decimals": 18,
        "priceUsd": 0.00638346511395226
      },
      {
        "address": "0xb435cb9cee20efce58c452f646552c3ad744ed64",
        "balance": "1",
        "balanceUsd": 0.0,
        "decimals": 18,
        "priceUsd": 0.0
      },
      {
        "address": "0xb676f87a6e701f0de8de5ab91b56b66109766db1",
        "balance": "13403378151942",
        "balanceUsd": 1.022721e-06,
        "decimals": 18,
        "priceUsd": 0.07630321278554111
      },
      {
        "address": "0xb96a7fa2dc5627eb76f91962e1e45e75e572c850",
        "balance": "1",
        "balanceUsd": 0.0,
        "decimals": 18,
        "priceUsd": 0.0
      },
      {
        "address": "0xb9e1fd5a02d3a33b25a14d661414e6ed6954a721",
        "balance": "60938221628952",
        "balanceUsd": 4.5426151e-05,
        "decimals": 18,
        "priceUsd": 0.7454459576607901
      },
      {
        "address": "0xbb22ff867f8ca3d5f2251b4084f6ec86d4666e14",
        "balance": "97143795177365",
        "balanceUsd": 0.000113851519,
        "decimals": 18,
        "priceUsd": 1.171989618527419
      },
      {
        "address": "0xbcd73d9c3de8884c9aaaf9b2e4f0a48a64f12a1b",
        "balance": "1",
        "balanceUsd": 0.0,
        "decimals": 18,
        "priceUsd": 0.0
      },
      {
        "address": "0xbf927b841994731c573bdf09ceb0c6b0aa887cdd",
        "balance": "0",
        "balanceUsd": 0.0,
        "decimals": 18,
        "priceUsd": 0.21031654431617447
      },
      {
        "address": "0xc0041ef357b183448b235a8ea73ce4e4ec8c265f",
        "balance": "0",
        "balanceUsd": 0.0,
        "decimals": 18,
        "priceUsd": 0.07732468713532828
      },
      {
        "address": "0xc08cd26474722ce93f4d0c34d16201461c10aa8c",
        "balance": "1232555985799891",
        "balanceUsd": 0.000176570462,
        "decimals": 18,
        "priceUsd": 0.14325553087284829
      },
      {
        "address": "0xc1cba3fcea344f92d9239c08c0568f6f2f0ee452",
        "balance": "0",
        "balanceUsd": 0.0,
        "decimals": 18,
        "priceUsd": 4539.994572541674
      },
      {
        "address": "0xc48823ec67720a04a9dfd8c7d109b2c3d6622094",
        "balance": "220162530092638",
        "balanceUsd": 1.813954e-06,
        "decimals": 18,
        "priceUsd": 0.0082391586862853
      },
      {
        "address": "0xc729777d0470f30612b1564fd96e8dd26f5814e3",
        "balance": "8444356179132",
        "balanceUsd": 1.369587e-06,
        "decimals": 18,
        "priceUsd": 0.16218964038304937
      },
      {
        "address": "0xca73ed1815e5915489570014e024b7ebe65de679",
        "balance": "225875842314075",
        "balanceUsd": 7.64755e-07,
        "decimals": 18,
        "priceUsd": 0.0033857310442809993
      },
      {
        "address": "0xcbb7c0000ab88b473b1f5afd9ef808440eed33bf",
        "balance": "75467",
        "balanceUsd": 0.0,
        "decimals": 8,
        "priceUsd": 0.0
      },
      {
        "address": "0xcd2f22236dd9dfe2356d7c543161d4d260fd9bcb",
        "balance": "0",
        "balanceUsd": 0.0,
        "decimals": 18,
        "priceUsd": 0.2827269125604089
      },
      {
        "address": "0xd01c8f05a9b7d5c2672a590b563ced2cb50d24a6",
        "balance": "1",
        "balanceUsd": 0.0,
        "decimals": 18,
        "priceUsd": 0.0
      },
      {
        "address": "0xd24ea96b9bf1af69d34e7fc8c6d740bae5f32b9b",
        "balance": "1",
        "balanceUsd": 0.0,
        "decimals": 18,
        "priceUsd": 0.0
      },
      {
        "address": "0xd262a4c7108c8139b2b189758e8d17c3dfc91a38",
        "balance": "0",
        "balanceUsd": 0.0,
        "decimals": 18,
        "priceUsd": 0.05072734278569005
      },
      {
        "address": "0xd403d1624daef243fbcbd4a80d8a6f36affe32b2",
        "balance": "52787601062",
        "balanceUsd": 8.93843e-07,
        "decimals": 18,
        "priceUsd": 16.932815275483616
      },
      {
        "address": "0xd4554bea546efa83c1e6b389ecac40ea999b3e78",
        "balance": "9451806248961860",
        "balanceUsd": 0.000936182598,
        "decimals": 18,
        "priceUsd": 0.09904800975852734
      },
      {
        "address": "0xd769d56f479e9e72a77bb1523e866a33098feec5",
        "balance": "153409995360875579",
        "balanceUsd": 0.000445635749,
        "decimals": 18,
        "priceUsd": 0.0029048677537211833
      },
      {
        "address": "0xda932bcc910ec2dbdcbc49e01f8a5b36be9deefb",
        "balance": "1",
        "balanceUsd": 0.0,
        "decimals": 18,
        "priceUsd": 0.0
      },
      {
        "address": "0xdbfefd2e8460a6ee4955a68582f85708baea60a3",
        "balance": "0",
        "balanceUsd": 0.0,
        "decimals": 18,
        "priceUsd": 3726.772975648495
      },
      {
        "address": "0xdcefd8c8fcc492630b943abcab3429f12ea9fea2",
        "balance": "0",
        "balanceUsd": 0.0,
        "decimals": 9,
        "priceUsd": 0.1312934387674124
      },
      {
        "address": "0xe1bfa25468af64e366ddafc9d91bcc6c97439a14",
        "balance": "56704705198713762",
        "balanceUsd": 0.000513190273,
        "decimals": 18,
        "priceUsd": 0.009050223800508609
      },
      {
        "address": "0xe22c243c7559c667a1eb94b593369d192c5fbac0",
        "balance": "216111154",
        "balanceUsd": 1.51524e-07,
        "decimals": 18,
        "priceUsd": 701.1388238102584
      },
      {
        "address": "0xe5020a6d073a794b6e7f05678707de47986fb0b6",
        "balance": "38342771555",
        "balanceUsd": 3.8322e-08,
        "decimals": 18,
        "priceUsd": 0.9994565423870788
      },
      {
        "address": "0xe642657e4f43e6dcf0bd73ef24008394574dee28",
        "balance": "2274985714322901",
        "balanceUsd": 8.73215e-07,
        "decimals": 18,
        "priceUsd": 0.000383832990948164
      },
      {
        "address": "0xeab49138ba2ea6dd776220fe26b7b8e446638956",
        "balance": "0",
        "balanceUsd": 0.0,
        "decimals": 18,
        "priceUsd": 0.07155473954334658
      },
      {
        "address": "0xed6e000def95780fb89734c07ee2ce9f6dcaf110",
        "balance": "822938552263560",
        "balanceUsd": 0.000251000883,
        "decimals": 18,
        "priceUsd": 0.305005619927976
      },
      {
        "address": "0xed7b04a3fdcc4b0718f76ab796d58f39212815cc",
        "balance": "1000000000000000000",
        "balanceUsd": 0.0,
        "decimals": 18,
        "priceUsd": 0.0
      },
      {
        "address": "0xeec468333ccc16d4bf1cef497a56cf8c0aae4ca3",
        "balance": "6795630367362885519",
        "balanceUsd": 0.006614964807,
        "decimals": 18,
        "priceUsd": 0.0009734144515180839
      },
      {
        "address": "0xef4461891dfb3ac8572ccf7c794664a8dd927945",
        "balance": "24041498211788716",
        "balanceUsd": 0.003378706729,
        "decimals": 18,
        "priceUsd": 0.14053644657908199
      },
      {
        "address": "0xf1a7000000950c7ad8aff13118bb7ab561a448ee",
        "balance": "216825930029491",
        "balanceUsd": 4.956164e-06,
        "decimals": 18,
        "priceUsd": 0.02285780102391797
      },
      {
        "address": "0xf3df0a31ec5ea438150987805e841f960b9471b6",
        "balance": "250441630520819",
        "balanceUsd": 8.904078e-06,
        "decimals": 18,
        "priceUsd": 0.035553506858090445
      },
      {
        "address": "0xf43eb8de897fbc7f2502483b2bef7bb9ea179229",
        "balance": "3094354419929955",
        "balanceUsd": 0.034631478607,
        "decimals": 18,
        "priceUsd": 11.191826761718815
      },
      {
        "address": "0xf4d97f2da56e8c3098f3a8d538db630a2606a024",
        "balance": "42318101892",
        "balanceUsd": 5.548151e-06,
        "decimals": 18,
        "priceUsd": 131.10586231808193
      },
      {
        "address": "0xf544251d25f3d243a36b07e7e7962a678f952691",
        "balance": "6056677373905592",
        "balanceUsd": 0.000474095608,
        "decimals": 18,
        "priceUsd": 0.07827651683740117
      },
      {
        "address": "0xf7c1cefcf7e1dd8161e00099facd3e1db9e528ee",
        "balance": "345096043232482727",
        "balanceUsd": 0.000309671159,
        "decimals": 18,
        "priceUsd": 0.0008973477520197179
      },
      {
        "address": "0xfaf87e196a29969094be35dfb0ab9d0b8518db84",
        "balance": "1000",
        "balanceUsd": 0.0,
        "decimals": 6,
        "priceUsd": 0.0
      },
      {
        "address": "0xfb584ace7f491e2930491a8d01a28db308aeb65f",
        "balance": "1",
        "balanceUsd": 0.0,
        "decimals": 18,
        "priceUsd": 0.0
      },
      {
        "address": "0xfc48314ad4ad5bd36a84e8307b86a68a01d95d9c",
        "balance": "9083099162843",
        "balanceUsd": 1.876612e-06,
        "decimals": 18,
        "priceUsd": 0.20660482594612717
      },
      {
        "address": "0xfd755cff1f0f65c1e163b33c66a0e082ce6f87ff",
        "balance": "1",
        "balanceUsd": 0.0,
        "decimals": 18,
        "priceUsd": 0.0
      },
      {
        "address": "0xfde4c96c8593536e31f229ea8f37b2ada2699bb2",
        "balance": "201",
        "balanceUsd": 0.00020094296,
        "decimals": 6,
        "priceUsd": 0.9997162166999343
      }
    ],
    "minUsd": 1.0
  },
  "state": {
    "last_tx_hash": "0xe53a50407596e96260ae7bf36939e67ac782df9d4f33b0714fdc15e3f7a2e31d",
    "last_update": 1761853214
  },
  "tokens": [
    {
      "address": "0x806041b6473da60abbe1b256d9a2749a151be6c6",
      "decimals": 9,
      "priceUsd": 517.921665917649,
      "source": "llama"
    }
  ],
  "updateTimestamp": 1761853214
}